django_composite_auto_field/__init__.py
django_composite_auto_field/fields.py
django_composite_auto_field/urls.py
django_composite_auto_field-0.1.5.dist-info/LICENSE
django_composite_auto_field-0.1.5.dist-info/METADATA
django_composite_auto_field-0.1.5.dist-info/WHEEL
django_composite_auto_field-0.1.5.dist-info/top_level.txt
django_composite_auto_field-0.1.5.dist-info/RECORD
